{"State.c3c4c5c4-4b91-42ce-a452-563d9d099e67": {"updated_at": "2024-03-17T14:26:34.658185", "name": "Arizona", "created_at": "2024-03-17T14:26:34.658095", "id": "c3c4c5c4-4b91-42ce-a452-563d9d099e67", "__class__": "State"}, "Place.d5ed2b93-559f-4f09-b9ea-4f1731d8effd": {"name": "My little house", "created_at": "2024-03-17T14:26:34.659583", "max_guest": 10, "number_rooms": 4, "price_by_night": 300, "updated_at": "2024-03-17T14:26:34.659771", "city_id": "0001", "longitude": -122.431297, "id": "d5ed2b93-559f-4f09-b9ea-4f1731d8effd", "latitude": 37.773972, "number_bathrooms": 2, "user_id": "0001", "__class__": "Place"}, "State.7bdef614-9d5c-48fa-8bbb-9357b1b17bfa": {"updated_at": "2024-03-17T14:26:34.565355", "name": "California", "created_at": "2024-03-17T14:26:34.565268", "id": "7bdef614-9d5c-48fa-8bbb-9357b1b17bfa", "__class__": "State"}}